ap_mal/__init__.py
ap_mal/__main__.py
ap_mal/ap.py
ap_mal/base.py
ap_mal/browsercookie.py
ap_mal/mal.py
ap_mal-0.1.0.dist-info/entry_points.txt
ap_mal-0.1.0.dist-info/LICENSE
ap_mal-0.1.0.dist-info/WHEEL
ap_mal-0.1.0.dist-info/METADATA
ap_mal-0.1.0.dist-info/RECORD
